{
  "$schema": "https://biomejs.dev/schemas/1.5.3/schema.json",
  "vcs": {
    "enabled": true,
    "clientKind": "git",
    "useIgnoreFile": true,
    "defaultBranch": "main"
  },
  "organizeImports": {
    "enabled": true
  },
  "formatter": {
    "indentStyle": "space",
    "lineWidth": 100
  },
  "linter": {
    "enabled": true,
    "rules": {
      "recommended": true,
      "security": {
        "noDangerouslySetInnerHtml": "off"
      },
      "suspicious": {
        "noArrayIndexKey": "off"
      }
    }
  },
  "javascript": {
    "formatter": {
      "arrowParentheses": "asNeeded"
    }
  }
}
